braq/__init__.py
braq/__main__.py
braq/configfile/__init__.py
braq/document/__init__.py
braq/errors/__init__.py
braq/filedoc/__init__.py
braq/fileio/__init__.py
braq/misc/__init__.py
braq/parser/__init__.py
braq/section/__init__.py
tests/__init__.py
tests/__main__.py
tests/test_configfile.py
tests/test_document.py
tests/test_filedoc.py
tests/test_fileio.py
tests/test_imports.py
tests/test_misc.py
tests/test_parser.py
tests/test_section.py
braq-0.0.11.dist-info/LICENSE
braq-0.0.11.dist-info/METADATA
braq-0.0.11.dist-info/WHEEL
braq-0.0.11.dist-info/entry_points.txt
braq-0.0.11.dist-info/top_level.txt
braq-0.0.11.dist-info/RECORD
